jpysocket/__init__.py
jpysocket-1.1.4.dist-info/LICENSE.txt
jpysocket-1.1.4.dist-info/METADATA
jpysocket-1.1.4.dist-info/WHEEL
jpysocket-1.1.4.dist-info/top_level.txt
jpysocket-1.1.4.dist-info/RECORD
