Metadata-Version: 2.1
Name: jpysocket
Version: 1.1.4
Summary: Decode The String Received From Java Socket And Encode The String for Send To The Java Socket
Home-page: UNKNOWN
Author: Ganesh Jagdale
Author-email: jagdaleganesh9545@gmail.com
License: UNKNOWN
Platform: UNKNOWN
Classifier: Programming Language :: Python :: 3
Classifier: License :: OSI Approved :: MIT License
Classifier: Operating System :: OS Independent
